oasees_sdk/cli/__init__.py
oasees_sdk/cli/cli.py
oasees_sdk/cli/commands/__init__.py
oasees_sdk/cli/commands/display_banner.py
oasees_sdk/cli/commands/jupyter_templating.py
oasees_sdk/cli/commands/mlops.py
oasees_sdk/cli/commands/telemetry.py
oasees_sdk/cli/commands/update.py
oasees_sdk/cli/ipfs_client.py
oasees_sdk/cli/oasees_ml_ops.py
oasees_sdk/oasees_sdk/__init__.py
oasees_sdk/oasees_sdk/cluster_ipfs_upload.py
oasees_sdk/oasees_sdk/deploy_pipeline.py
oasees_sdk/oasees_sdk/mlops/__init__.py
oasees_sdk/oasees_sdk/mlops/env_vars.py
oasees_sdk/oasees_sdk/mlops/ml_template.py
oasees_sdk/oasees_sdk/mlops/templating_functions.py
oasees_sdk/oasees_sdk/mlops/util_files.py
oasees_sdk/oasees_sdk/sdk.py
oasees_sdk/oasees_sdk/training_workload.py
oasees_sdk/oasees_sdk/utility_functions.py
oasees_sdk-0.7.4.dist-info/METADATA
oasees_sdk-0.7.4.dist-info/WHEEL
oasees_sdk-0.7.4.dist-info/entry_points.txt
oasees_sdk-0.7.4.dist-info/licenses/LICENSE
oasees_sdk-0.7.4.dist-info/RECORD
