Metadata-Version: 2.4
Name: oasees_sdk
Version: 0.7.4
Summary: Oasees SDK
License-File: LICENSE
Author: Achilleas Economopoulos
Classifier: License :: OSI Approved :: MIT License
Classifier: Operating System :: OS Independent
Classifier: Programming Language :: Python :: 2
Classifier: Programming Language :: Python :: 2.7
Classifier: Programming Language :: Python :: 3
Classifier: Programming Language :: Python :: 3.4
Classifier: Programming Language :: Python :: 3.5
Classifier: Programming Language :: Python :: 3.6
Classifier: Programming Language :: Python :: 3.7
Classifier: Programming Language :: Python :: 3.8
Classifier: Programming Language :: Python :: 3.9
Classifier: Programming Language :: Python :: 3.10
Classifier: Programming Language :: Python :: 3.11
Classifier: Programming Language :: Python :: 3.12
Classifier: Programming Language :: Python :: 3.13
Classifier: Programming Language :: Python :: 3.14
Requires-Dist: Click
Requires-Dist: ipylab
Requires-Dist: jupytext
Requires-Dist: kubernetes
Requires-Dist: numpy (==1.26.4)
Requires-Dist: python-dotenv
Requires-Dist: requests
